dynamixel_control/__init__.py
dynamixel_control/dxl.py
dynamixel_control/dynamixel.py
dynamixel_control-0.2.4.dist-info/LICENSE
dynamixel_control-0.2.4.dist-info/METADATA
dynamixel_control-0.2.4.dist-info/WHEEL
dynamixel_control-0.2.4.dist-info/top_level.txt
dynamixel_control-0.2.4.dist-info/RECORD
