Metadata-Version: 2.1
Name: dynamixel-control
Version: 0.2.4
Summary: A python package for interfacing with Dynamixel XL-330 motors.
Author-email: Kyle <dufrenek@oregonstate.edu>
Project-URL: Homepage, https://github.com/OSUrobotics/dynamixel-control
Classifier: Programming Language :: Python :: 3
Classifier: License :: OSI Approved :: BSD License
Classifier: Operating System :: OS Independent
Requires-Python: >=3.8
License-File: LICENSE
Requires-Dist: dynamixel-sdk >3.6.0
Requires-Dist: numpy >1.23.0
